teleexception/__init__.py
teleexception/status/__init__.py
teleexception/status/http_status.py
teleexception/status/http_status_digital_life.py
teleexception/status/http_status_electron_fence.py
teleexception/status/status_exception.py
teleexception/status/status_exception_digital_life.py
teleexception/status/status_exception_electron_fence.py
teleexception-0.3.54.dist-info/METADATA
teleexception-0.3.54.dist-info/WHEEL
teleexception-0.3.54.dist-info/top_level.txt
teleexception-0.3.54.dist-info/RECORD
