Metadata-Version: 2.1
Name: teleexception
Version: 0.3.54
Summary: Python Package for tele exception
Author: imason
Author-email: 635761952@qq.com
Keywords: python exception
Classifier: Programming Language :: Python :: 3
Classifier: License :: OSI Approved :: MIT License
Classifier: Operating System :: OS Independent
Requires-Python: >=3.6,
